parent_aware/__init__.py
parent_aware/parent_aware.py
parent_aware/test_parent_aware.py
parent_aware-0.0.1.dist-info/LICENSE
parent_aware-0.0.1.dist-info/METADATA
parent_aware-0.0.1.dist-info/WHEEL
parent_aware-0.0.1.dist-info/top_level.txt
parent_aware-0.0.1.dist-info/RECORD
